xiaoya/__init__.py
xiaoya/aliyundrive.py
xiaoya/attribute.py
xiaoya/clear.py
xiaoya/command.py
xiaoya/exception.py
xiaoya/utils.py
xiaoya-0.1.6.dist-info/LICENSE
xiaoya-0.1.6.dist-info/METADATA
xiaoya-0.1.6.dist-info/WHEEL
xiaoya-0.1.6.dist-info/entry_points.txt
xiaoya-0.1.6.dist-info/top_level.txt
xiaoya-0.1.6.dist-info/zip-safe
xiaoya-0.1.6.dist-info/RECORD
